Classfile /Users/xiabaike/workspace/study/algorithm/src/main/java/com/xiabaike/algo/main/Test2.class
  Last modified 2022年3月18日; size 1428 bytes
  MD5 checksum a8286fd2dbf702683396801cec3244e8
  Compiled from "Test2.java"
public class com.xiabaike.algo.main.Test2
  minor version: 0
  major version: 55
  flags: (0x0021) ACC_PUBLIC, ACC_SUPER
  this_class: #16                         // com/xiabaike/algo/main/Test2
  super_class: #17                        // java/lang/Object
  interfaces: 0, fields: 1, methods: 4, attributes: 3
Constant pool:
   #1 = Methodref          #17.#32        // java/lang/Object."<init>":()V
   #2 = Class              #33            // java/lang/Thread
   #3 = InvokeDynamic      #0:#38         // #0:run:()Ljava/lang/Runnable;
   #4 = Methodref          #2.#39         // java/lang/Thread."<init>":(Ljava/lang/Runnable;)V
   #5 = Methodref          #2.#40         // java/lang/Thread.start:()V
   #6 = Long               2000l
   #8 = Methodref          #2.#41         // java/lang/Thread.sleep:(J)V
   #9 = Class              #42            // java/lang/InterruptedException
  #10 = Methodref          #9.#43         // java/lang/InterruptedException.printStackTrace:()V
  #11 = Fieldref           #16.#44        // com/xiabaike/algo/main/Test2.isOver:Z
  #12 = Fieldref           #45.#46        // java/lang/System.out:Ljava/io/PrintStream;
  #13 = Methodref          #47.#48        // java/io/PrintStream.println:(Z)V
  #14 = String             #49            // it\'s end
  #15 = Methodref          #47.#50        // java/io/PrintStream.println:(Ljava/lang/String;)V
  #16 = Class              #51            // com/xiabaike/algo/main/Test2
  #17 = Class              #52            // java/lang/Object
  #18 = Utf8               isOver
  #19 = Utf8               Z
  #20 = Utf8               <init>
  #21 = Utf8               ()V
  #22 = Utf8               Code
  #23 = Utf8               LineNumberTable
  #24 = Utf8               main
  #25 = Utf8               ([Ljava/lang/String;)V
  #26 = Utf8               StackMapTable
  #27 = Class              #53            // "[Ljava/lang/String;"
  #28 = Utf8               lambda$main$0
  #29 = Utf8               <clinit>
  #30 = Utf8               SourceFile
  #31 = Utf8               Test2.java
  #32 = NameAndType        #20:#21        // "<init>":()V
  #33 = Utf8               java/lang/Thread
  #34 = Utf8               BootstrapMethods
  #35 = MethodHandle       6:#54          // REF_invokeStatic java/lang/invoke/LambdaMetafactory.metafactory:(Ljava/lang/invoke/MethodHandles$Lookup;Ljava/lang/String;Ljava/lang/invoke/MethodType;Ljava/lang/invoke/MethodType;Ljava/lang/invoke/MethodHandle;Ljava/lang/invoke/MethodType;)Ljava/lang/invoke/CallSite;
  #36 = MethodType         #21            //  ()V
  #37 = MethodHandle       6:#55          // REF_invokeStatic com/xiabaike/algo/main/Test2.lambda$main$0:()V
  #38 = NameAndType        #56:#57        // run:()Ljava/lang/Runnable;
  #39 = NameAndType        #20:#58        // "<init>":(Ljava/lang/Runnable;)V
  #40 = NameAndType        #59:#21        // start:()V
  #41 = NameAndType        #60:#61        // sleep:(J)V
  #42 = Utf8               java/lang/InterruptedException
  #43 = NameAndType        #62:#21        // printStackTrace:()V
  #44 = NameAndType        #18:#19        // isOver:Z
  #45 = Class              #63            // java/lang/System
  #46 = NameAndType        #64:#65        // out:Ljava/io/PrintStream;
  #47 = Class              #66            // java/io/PrintStream
  #48 = NameAndType        #67:#68        // println:(Z)V
  #49 = Utf8               it\'s end
  #50 = NameAndType        #67:#69        // println:(Ljava/lang/String;)V
  #51 = Utf8               com/xiabaike/algo/main/Test2
  #52 = Utf8               java/lang/Object
  #53 = Utf8               [Ljava/lang/String;
  #54 = Methodref          #70.#71        // java/lang/invoke/LambdaMetafactory.metafactory:(Ljava/lang/invoke/MethodHandles$Lookup;Ljava/lang/String;Ljava/lang/invoke/MethodType;Ljava/lang/invoke/MethodType;Ljava/lang/invoke/MethodHandle;Ljava/lang/invoke/MethodType;)Ljava/lang/invoke/CallSite;
  #55 = Methodref          #16.#72        // com/xiabaike/algo/main/Test2.lambda$main$0:()V
  #56 = Utf8               run
  #57 = Utf8               ()Ljava/lang/Runnable;
  #58 = Utf8               (Ljava/lang/Runnable;)V
  #59 = Utf8               start
  #60 = Utf8               sleep
  #61 = Utf8               (J)V
  #62 = Utf8               printStackTrace
  #63 = Utf8               java/lang/System
  #64 = Utf8               out
  #65 = Utf8               Ljava/io/PrintStream;
  #66 = Utf8               java/io/PrintStream
  #67 = Utf8               println
  #68 = Utf8               (Z)V
  #69 = Utf8               (Ljava/lang/String;)V
  #70 = Class              #73            // java/lang/invoke/LambdaMetafactory
  #71 = NameAndType        #74:#78        // metafactory:(Ljava/lang/invoke/MethodHandles$Lookup;Ljava/lang/String;Ljava/lang/invoke/MethodType;Ljava/lang/invoke/MethodType;Ljava/lang/invoke/MethodHandle;Ljava/lang/invoke/MethodType;)Ljava/lang/invoke/CallSite;
  #72 = NameAndType        #28:#21        // lambda$main$0:()V
  #73 = Utf8               java/lang/invoke/LambdaMetafactory
  #74 = Utf8               metafactory
  #75 = Class              #80            // java/lang/invoke/MethodHandles$Lookup
  #76 = Utf8               Lookup
  #77 = Utf8               InnerClasses
  #78 = Utf8               (Ljava/lang/invoke/MethodHandles$Lookup;Ljava/lang/String;Ljava/lang/invoke/MethodType;Ljava/lang/invoke/MethodType;Ljava/lang/invoke/MethodHandle;Ljava/lang/invoke/MethodType;)Ljava/lang/invoke/CallSite;
  #79 = Class              #81            // java/lang/invoke/MethodHandles
  #80 = Utf8               java/lang/invoke/MethodHandles$Lookup
  #81 = Utf8               java/lang/invoke/MethodHandles
{
  public com.xiabaike.algo.main.Test2();
    descriptor: ()V
    flags: (0x0001) ACC_PUBLIC
    Code:
      stack=1, locals=1, args_size=1
         0: aload_0
         1: invokespecial #1                  // Method java/lang/Object."<init>":()V
         4: return
      LineNumberTable:
        line 3: 0

  public static void main(java.lang.String[]);
    descriptor: ([Ljava/lang/String;)V
    flags: (0x0009) ACC_PUBLIC, ACC_STATIC
    Code:
      stack=3, locals=3, args_size=1
         0: new           #2                  // class java/lang/Thread
         3: dup
         4: invokedynamic #3,  0              // InvokeDynamic #0:run:()Ljava/lang/Runnable;
         9: invokespecial #4                  // Method java/lang/Thread."<init>":(Ljava/lang/Runnable;)V
        12: astore_1
        13: aload_1
        14: invokevirtual #5                  // Method java/lang/Thread.start:()V
        17: ldc2_w        #6                  // long 2000l
        20: invokestatic  #8                  // Method java/lang/Thread.sleep:(J)V
        23: goto          31
        26: astore_2
        27: aload_2
        28: invokevirtual #10                 // Method java/lang/InterruptedException.printStackTrace:()V
        31: iconst_1
        32: putstatic     #11                 // Field isOver:Z
        35: return
      Exception table:
         from    to  target type
            17    23    26   Class java/lang/InterruptedException
      LineNumberTable:
        line 8: 0
        line 14: 13
        line 16: 17
        line 19: 23
        line 17: 26
        line 18: 27
        line 20: 31
        line 21: 35
      StackMapTable: number_of_entries = 2
        frame_type = 255 /* full_frame */
          offset_delta = 26
          locals = [ class "[Ljava/lang/String;", class java/lang/Thread ]
          stack = [ class java/lang/InterruptedException ]
        frame_type = 4 /* same */

  static {};
    descriptor: ()V
    flags: (0x0008) ACC_STATIC
    Code:
      stack=1, locals=0, args_size=0
         0: iconst_0
         1: putstatic     #11                 // Field isOver:Z
         4: return
      LineNumberTable:
        line 5: 0
}
SourceFile: "Test2.java"
InnerClasses:
  public static final #76= #75 of #79;    // Lookup=class java/lang/invoke/MethodHandles$Lookup of class java/lang/invoke/MethodHandles
BootstrapMethods:
  0: #35 REF_invokeStatic java/lang/invoke/LambdaMetafactory.metafactory:(Ljava/lang/invoke/MethodHandles$Lookup;Ljava/lang/String;Ljava/lang/invoke/MethodType;Ljava/lang/invoke/MethodType;Ljava/lang/invoke/MethodHandle;Ljava/lang/invoke/MethodType;)Ljava/lang/invoke/CallSite;
    Method arguments:
      #36 ()V
      #37 REF_invokeStatic com/xiabaike/algo/main/Test2.lambda$main$0:()V
      #36 ()V
